nbrshell/__init__.py
nbrshell/exec_shell_script.py
nbrshell/exec_shell_script_fn.py
nbrshell/nbrshell_common.py
nbrshell/pbrun_as.py
nbrshell/pbrun_as_fn.py
nbrshell/pbrun_as_oracle.py
nbrshell/pbrun_as_oracle_fn.py
nbrshell/pbrun_sqlplus.py
nbrshell-1.0.14.dist-info/METADATA
nbrshell-1.0.14.dist-info/WHEEL
nbrshell-1.0.14.dist-info/top_level.txt
nbrshell-1.0.14.dist-info/RECORD
