Metadata-Version: 2.1
Name: nbrshell
Version: 1.0.14
Summary: Jupyter Notebook "cell magic" functions to remotely execute shell script typed in a notebook cell.
Home-page: https://github.com/abalbekov/nbrshell
Author: A.Balbekov
Author-email: albert.y.balbekov@gmail.com
License: BSD License
Keywords: remote shell script execution,remote shell,shell,sqlplus
Requires-Dist: paramiko
